<?xml version="1.0" ?>
<State openmmVersion="7.3.1" time=".4400000000000003" type="State" version="1">
	<PeriodicBoxVectors>
		<A x="2" y="0" z="0"/>
		<B x="0" y="2" z="0"/>
		<C x="0" y="0" z="2"/>
	</PeriodicBoxVectors>
	<Parameters/>
	<Energies KineticEnergy="16.352938070757318" PotentialEnergy="-573.1898712903325"/>
	<Positions>
		<Position x=".2664085351742777" y=".3518887757282141" z="-.22522390455018856"/>
		<Position x="-.45394952292749063" y=".44065298074192466" z="-.036263842929914344"/>
		<Position x="-.07261039082202676" y="-.23113950716784074" z="-.5533247333092279"/>
		<Position x=".6477992850702604" y="-.06710959387987948" z="-.4244430554721058"/>
		<Position x="-.5608796255972394" y="-.24392330708117035" z="-1.1224635218182941"/>
		<Position x="-.4200807537345431" y="-.7957375904197861" z="-.6344374373628561"/>
		<Position x="-.7845909034940761" y="-.03735061358464948" z="-1.8078754662864838"/>
		<Position x="-.7192547332338209" y="-.7793130229460397" z="-1.8957627869760327"/>
		<Position x="-.07602969324647846" y="-.26634980518323187" z="-1.8973299646045432"/>
		<Position x=".0708647709262824" y="-.10630038852922583" z="-2.6151781273716415"/>
		<Position x=".629552136984804" y="-.08282612752398726" z="-1.721339578659582"/>
		<Position x=".567430345865702" y="-.812760773729418" z="-1.560603168336545"/>
		<Position x=".3262659513400864" y=".5763487828910794" z="-1.5315872971159616"/>
		<Position x="1.0526969627621516" y=".39090307640848726" z="-1.5517832347325597"/>
		<Position x="-.13533259053506902" y="1.05028222602693" z="-1.1782972219550705"/>
		<Position x="-.07782113045245906" y="1.0542777323119732" z="-1.9260782513196886"/>
	</Positions>
	<Velocities>
		<Velocity x="-.04428424847739976" y="-.026795764175069348" z="-.038414570925138225"/>
		<Velocity x="-.021187113959442172" y="-.014440052564901329" z=".04392011550300862"/>
		<Velocity x="-.16197462255895523" y="-.028936319305089553" z=".08682888942508349"/>
		<Velocity x="-.1411256970121455" y=".0294073616183832" z="-.10335395225938848"/>
		<Velocity x="-.04703270866803777" y="-.11156768295776387" z="-.01011437909359536"/>
		<Velocity x="-.020076854474548878" y="-.01284239881047533" z=".09389194041176108"/>
		<Velocity x="-.030626901496089154" y="-.000388200576123543" z=".01802788174516401"/>
		<Velocity x="-.12324552993840943" y="-.00936633041854762" z=".02475591801389676"/>
		<Velocity x=".029756310708561884" y=".1699665576543108" z=".059286420588477995"/>
		<Velocity x="-.14543384854969754" y=".19825815872561992" z=".029631481369385426"/>
		<Velocity x=".10063567360438785" y="-.08363667113024942" z=".04054622266322916"/>
		<Velocity x="-.017073098138364884" y="-.10228726288212808" z="-.09038001309567001"/>
		<Velocity x="-.04837662530894349" y="-.09932769863187918" z="-.1400631106198258"/>
		<Velocity x=".011023355677064473" y=".11290979307864157" z=".021179792936276698"/>
		<Velocity x=".130810951896132" y=".023235720833136853" z="-.07120733483749753"/>
		<Velocity x=".015165940822378654" y="-.08006433788421141" z="-.080563723670668"/>
	</Velocities>
	<Forces>
		<Force x="33.24266070356233" y="-87.151223506907" z="10.561038509659973"/>
		<Force x="-36.300962828795505" y="28.727847207653284" z="12.281193751562533"/>
		<Force x=".9039676549596791" y="24.222809183580935" z="-40.35934920882091"/>
		<Force x="31.173452477168382" y="-23.940306876444765" z="30.966107074149704"/>
		<Force x="-24.047658189239243" y="-30.239763872143307" z="-44.94268331586826"/>
		<Force x="23.633184506551117" y="43.24251643424169" z="-4.0663926269765085"/>
		<Force x="2.022909878407125" y="-27.541549084054793" z="26.597573796379194"/>
		<Force x="-17.434703375083384" y="4.6997084295624845" z="39.17006395023681"/>
		<Force x="4.772076052382355" y="7.153781403121407" z="56.92345564627649"/>
		<Force x="49.99408249008678" y="38.08412978600662" z="-4.996531067516784"/>
		<Force x="-42.0577017222652" y="-9.044110042683435" z="2.828836564970124"/>
		<Force x="-23.854481993652044" y="-1.6035851024325325" z="1.6866164964478276"/>
		<Force x="52.99072492646022" y="60.94218915405387" z="-3.4836937866611635"/>
		<Force x="-44.10973904099533" y="25.66336671366622" z="-25.15341391725862"/>
		<Force x="-28.543309922800358" y="-35.821579532682364" z="-91.30889045641335"/>
		<Force x="17.61550148269461" y="-17.394236374212074" z="33.29606668248432"/>
	</Forces>
</State>
