<?xml version="1.0" ?>
<State openmmVersion="7.3.1" time=".045" type="State" version="1">
	<PeriodicBoxVectors>
		<A x="2" y="0" z="0"/>
		<B x="0" y="2" z="0"/>
		<C x="0" y="0" z="2"/>
	</PeriodicBoxVectors>
	<Parameters/>
	<Energies KineticEnergy="513.1923868919143" PotentialEnergy="-574.496311658193"/>
	<Positions>
		<Position x=".21160682770888245" y=".3405811855080006" z="-.2025941387766647"/>
		<Position x="-.49498662124459303" y=".48490945736907465" z=".005658504929633289"/>
		<Position x="-.13380810768156745" y="-.23753947656030816" z="-.5524355726052279"/>
		<Position x=".6002292557437202" y="-.08953223184130368" z="-.4285452989780459"/>
		<Position x="-.5957659411803131" y="-.33276142627102845" z="-1.115088966124217"/>
		<Position x="-.4888098846217051" y="-.7458023550822068" z="-.5125394108509109"/>
		<Position x="-.8484195080194367" y="-.030411394210236073" z="-1.7693058894543061"/>
		<Position x="-.6793626506216577" y="-.7651664176099047" z="-1.769615043823026"/>
		<Position x="-.13955683059935844" y="-.2532934968967574" z="-1.8936374480524523"/>
		<Position x="-.025941570174286322" y=".014330440287372882" z="-2.5846350697109473"/>
		<Position x=".5558703074538623" y="-.057687342812708244" z="-1.6969341009168848"/>
		<Position x=".5903799029076372" y="-.789984646977304" z="-1.53932557672661"/>
		<Position x=".28975593164351454" y=".6129723002832334" z="-1.491909406963689"/>
		<Position x="1.0034546595506517" y=".4065031332106214" z="-1.5948447437784186"/>
		<Position x="-.2777183783401247" y="1.001902591583787" z="-1.1934133286709463"/>
		<Position x="-.07402987486265714" y="1.099447233904838" z="-1.90858363939637"/>
	</Positions>
	<Velocities>
		<Velocity x=".23794625768323585" y=".37387805303484845" z=".2511870395519755"/>
		<Velocity x="-.04318745441421745" y="-.013943850372932776" z=".016614729578457582"/>
		<Velocity x="-1.202867316722811" y="-.3782762589958466" z="-.7734762193924327"/>
		<Velocity x=".37055749670260596" y="-.09950425211568137" z=".09205329847312704"/>
		<Velocity x=".7238022330498195" y="-.4689825556906668" z="1.5910545475563698"/>
		<Velocity x="-.15036497483897904" y=".2660885901460963" z="-.47811727819675465"/>
		<Velocity x="-.46186656889903865" y=".45233805239785346" z="-.5800942196921621"/>
		<Velocity x=".0492325993066034" y="-.20570512772115634" z="-.06425368221192329"/>
		<Velocity x=".21486628690466358" y=".08452392785495144" z="-.012146917369859622"/>
		<Velocity x=".09167297147922443" y=".039629107183354606" z=".017929962954088552"/>
		<Velocity x="-.04257412875043887" y="-.045035812743754455" z=".09316191382677808"/>
		<Velocity x="-.03410098420528751" y="-.05090343105897954" z="-.06228133293246785"/>
		<Velocity x="-.021178227215157275" y=".04234665457429898" z="-.10092334033231509"/>
		<Velocity x=".02979389577877356" y=".09975279287036676" z=".05225770605101765"/>
		<Velocity x=".0073258204520754155" y=".005771594877046482" z="-.0329580526379214"/>
		<Velocity x="-.07461853741813351" y=".22597135453192863" z="-.022794532917513877"/>
	</Velocities>
	<Forces>
		<Force x="27.898021158915046" y="-33.087950056334265" z="-22.177983462354312"/>
		<Force x="-8.704042697647687" y="-4.579248950360737" z="-32.314083307216364"/>
		<Force x="-.31279435431061753" y="17.07220566563848" z="-38.70559950889718"/>
		<Force x="44.037214958948894" y="28.813777040186757" z="64.28552250607692"/>
		<Force x="7.480930153353264" y="37.011994637085934" z="-8.04006335707793"/>
		<Force x="-7.7061267111214775" y="-11.217711112953054" z="-5.6921908759585875"/>
		<Force x="26.1543162497178" y="-12.622767873599019" z="10.349135357755715"/>
		<Force x="-15.953521789683736" y="35.03752139457468" z="-18.714820522954106"/>
		<Force x="4.056565836167673" y="22.4281837182931" z="58.54364670863235"/>
		<Force x="21.23266164043121" y="-53.27902786558438" z="-12.51891494684208"/>
		<Force x="-18.46626679242495" y="-9.78242706074106" z="-39.647222542836936"/>
		<Force x="-28.542624209449095" y="-39.89858423793307" z="-1.5662103786686092"/>
		<Force x="-6.904032894359506" y="21.049926193137495" z="20.980639919548402"/>
		<Force x="-25.566030825735965" y="35.933378823890465" z="9.95260913309258"/>
		<Force x="8.729139387334348" y="-41.56967267429188" z="-40.21307742051246"/>
		<Force x="-27.433415785855424" y="8.690403789502014" z="55.47861865867708"/>
	</Forces>
</State>
