<?xml version="1.0" ?>
<State openmmVersion="7.3.1" time=".05499999999999999" type="State" version="1">
	<PeriodicBoxVectors>
		<A x="2" y="0" z="0"/>
		<B x="0" y="2" z="0"/>
		<C x="0" y="0" z="2"/>
	</PeriodicBoxVectors>
	<Parameters/>
	<Energies KineticEnergy="1359.1958842534318" PotentialEnergy="-572.7766364899946"/>
	<Positions>
		<Position x=".19773168660675938" y=".30568039345269665" z="-.19759686523345724"/>
		<Position x="-.5230413534840759" y=".45193702897482724" z="-.06165032623285545"/>
		<Position x="-.09539118441121622" y="-.2372300926061627" z="-.578329796137208"/>
		<Position x=".5985997122273006" y="-.06203791916106903" z="-.4652076905842818"/>
		<Position x="-.6081771232593692" y="-.30551127917878085" z="-1.1844649883561698"/>
		<Position x="-.38276632442453135" y="-.8312527895900448" z="-.6480252500734021"/>
		<Position x="-.8599145102299163" y=".030502339373422865" z="-1.7587194984645147"/>
		<Position x="-.8059508154710997" y="-.7022201578327308" z="-1.8321265288535122"/>
		<Position x="-.18806677528741225" y="-.2530341402214107" z="-1.8584130678527016"/>
		<Position x=".12607025916622874" y="-.15498191604146175" z="-2.5370581031949024"/>
		<Position x=".5374076066513332" y="-.04817993648151751" z="-1.7991996637973016"/>
		<Position x=".586298143082242" y="-.7625966232755881" z="-1.574164612950231"/>
		<Position x=".2999068779085812" y=".6080276750448672" z="-1.5251233348870932"/>
		<Position x="1.016337646428656" y=".4317829597877853" z="-1.6590438600289599"/>
		<Position x="-.263170877676224" y=".9937551996998563" z="-1.2137824830318968"/>
		<Position x="-.10641393831212131" y="1.0793905631747196" z="-1.9422484811781315"/>
	</Positions>
	<Velocities>
		<Velocity x="-.4210159067185859" y="-.45117603371064297" z="-.5308314672433145"/>
		<Velocity x=".03157172452494805" y=".03723558281818473" z="-.0279298142691356"/>
		<Velocity x="1.9887675261526376" y=".7641248668959377" z="1.657002732630497"/>
		<Velocity x="-.769801544281079" y="-.03426694475857639" z=".05067806417234921"/>
		<Velocity x="-1.7464642143529163" y="1.0052117407248762" z="-2.866602175479338"/>
		<Velocity x=".3422597631442814" y="-.7868589257213676" z=".7159671393864198"/>
		<Velocity x=".7896489729753098" y="-1.0093318531626774" z=".6640839972225088"/>
		<Velocity x="-.019425430026331902" y=".44373499893921586" z="-.11368350793579118"/>
		<Velocity x="-.6778982723590843" y=".09343344370247308" z=".2928936189941389"/>
		<Velocity x="-.05935142400907978" y="-.05967000253063737" z="-.02343122790007257"/>
		<Velocity x=".14823901869804867" y=".031131363604812445" z=".10845513478892066"/>
		<Velocity x=".08424838773921639" y="-.09210770192340512" z="-.01756533872381283"/>
		<Velocity x=".09916304173464008" y="-.005262289591589919" z=".0720494877579192"/>
		<Velocity x=".05853583588528721" y="-.029228630962974123" z="-.009948592281006086"/>
		<Velocity x=".07293079090062715" y=".053133990124187847" z=".005861926496075753"/>
		<Velocity x=".00417632998039319" y=".06905924218809645" z="-.012794100582125267"/>
	</Velocities>
	<Forces>
		<Force x="11.016832902819974" y="-25.248294651991035" z="-57.44147136667964"/>
		<Force x="-20.133652243400373" y="-26.679613118798688" z="-20.735440398690436"/>
		<Force x="-3.8647810572694556" y="22.363859884484302" z="8.118143341991008"/>
		<Force x="69.73767247958558" y="41.43947127465814" z="12.681327949850598"/>
		<Force x="4.436940933709069" y="15.908704021226672" z="-17.17514322173385"/>
		<Force x="-21.892958178631396" y="-6.537495770267398" z="38.98469542630623"/>
		<Force x="-37.70939823340747" y="-97.58987617672537" z="-11.572968037861765"/>
		<Force x="17.81708284768565" y="38.382113345847756" z="-10.502156643918763"/>
		<Force x="19.377040359125694" y="24.56980573987305" z="-1.1515188290052194"/>
		<Force x="-40.881852205006176" y="78.81064412121145" z="-119.84880107104115"/>
		<Force x="-18.999413274450433" y="-35.0362175299832" z="33.72965154018155"/>
		<Force x="6.434638671016113" y="-122.15352075704304" z="88.97384562034487"/>
		<Force x=".2785697888118648" y="51.060175554491266" z="25.72148876539495"/>
		<Force x="-34.2545230008253" y="21.693281981168" z="21.869720453203907"/>
		<Force x="56.13843953197793" y="19.771836420579234" z="-8.723228659300602"/>
		<Force x="-7.50063050025387" y="-.754864801987992" z="17.071852746772528"/>
	</Forces>
</State>
