<?xml version="1.0" ?>
<State openmmVersion="7.3.1" time=".05999999999999999" type="State" version="1">
	<PeriodicBoxVectors>
		<A x="2" y="0" z="0"/>
		<B x="0" y="2" z="0"/>
		<C x="0" y="0" z="2"/>
	</PeriodicBoxVectors>
	<Parameters/>
	<Energies KineticEnergy="55.69757998082646" PotentialEnergy="-498.03283564190946"/>
	<Positions>
		<Position x=".3344476869071473" y="-.24559206298035557" z=".2574376903172892"/>
		<Position x=".1851224667311876" y="-.5806282277895086" z="-.3967426584621849"/>
		<Position x=".9533407687568237" y="-.029713339903149803" z=".62195108599729"/>
		<Position x=".2316445492843879" y=".16342138198136463" z=".6880631402261604"/>
		<Position x="1.2714796413620286" y="-.12258483003466533" z="-.05080381353407759"/>
		<Position x="1.443139304937786" y=".0856416830174113" z=".6489148942680903"/>
		<Position x="1.239037751182159" y=".6006179102823641" z=".14477336388748294"/>
		<Position x="1.6651064771579527" y=".4411819071871026" z="-.4511792186405021"/>
		<Position x=".7528926045976676" y=".7045762309838999" z="-.41359593061721867"/>
		<Position x=".7917894672264818" y="1.1210238329767106" z=".20907597944605252"/>
		<Position x=".01334975632766772" y=".8018323628324245" z="-.27119044589888974"/>
		<Position x=".48050857107193085" y=".5622505099189705" z="-.8204151579778354"/>
		<Position x="-.467374909150471" y="1.0749482977253395" z=".21731379921350247"/>
		<Position x="-.6379786115594569" y=".9127715517109424" z="-.488555056958472"/>
		<Position x="-.5313891366804537" y=".48245805138432063" z="-.22734008844502135"/>
		<Position x="-.8895674726619663" y="-.10663248377904451" z=".07141337505829319"/>
	</Positions>
	<Velocities>
		<Velocity x=".04077353066274103" y="-.13887110568541194" z=".09269982274748845"/>
		<Velocity x="-.14180067854163148" y="-.23629247988701252" z=".18410467913801964"/>
		<Velocity x="-.005233845593233255" y="-.20532683062406062" z=".21046831495268314"/>
		<Velocity x="-.015449901460917737" y="-.12214499244117549" z="-.1322283669250135"/>
		<Velocity x="-.12848989069800254" y=".07132793640665658" z=".11623799321498068"/>
		<Velocity x="-.10341846431316526" y=".010751467730707454" z=".12539172542045396"/>
		<Velocity x="-.16562242152220463" y=".10497320379643238" z="-.03927966628895496"/>
		<Velocity x=".0010574350073344618" y=".047348630974541894" z=".11443713222992757"/>
		<Velocity x=".14709318822938577" y=".2794534928494352" z="-.08684190622105792"/>
		<Velocity x=".006956535610425085" y=".2116911520546605" z="-.023678627220796722"/>
		<Velocity x="-.37768100920935915" y=".27648688225019313" z=".2537533662075542"/>
		<Velocity x="-.06689199153361303" y="-.1766102562865468" z="-.11442622522068735"/>
		<Velocity x="-.034502796633995025" y="-.058835624718778234" z="-.33918540708865463"/>
		<Velocity x="-.1085250217994771" y=".08015905057414674" z=".024941295711700118"/>
		<Velocity x=".11712069562492822" y=".15799665282901776" z=".004874221765799325"/>
		<Velocity x=".08897482114107458" y=".09354079629491086" z=".05495342149488269"/>
	</Velocities>
	<Forces>
		<Force x="-2.8098316944663253" y="-7.65248930595736" z="-3.7776047518539855"/>
		<Force x="-6.163982229260085" y="82.60855178447031" z="23.604320289195485"/>
		<Force x="-19.505204867624425" y="16.58981519701946" z="-47.26660289695997"/>
		<Force x="-43.47184819695413" y="-97.17318101333612" z="58.509497916637315"/>
		<Force x="-19.098291915876427" y="46.98131669566317" z=".012880520790046646"/>
		<Force x="6.33912274964765" y="2.271653424804988" z="50.714045771343024"/>
		<Force x="14.454122606533033" y="10.276185488581191" z="-.5389656280467161"/>
		<Force x="-29.021462487773675" y="15.264558073407922" z="-43.85822042106202"/>
		<Force x="-41.42434117717356" y="-32.52643306497744" z="33.73021349854841"/>
		<Force x="9.529691301300637" y="-4.47260394707341" z="-7.818049787749882"/>
		<Force x="2.3505847107061353" y="21.38615235133693" z="-73.47691753594017"/>
		<Force x="77.75002922005913" y="-48.470723596367215" z="-45.353669317753145"/>
		<Force x="20.19207580604556" y="-19.124464924470963" z="-5.185845358670772"/>
		<Force x="46.2417157729019" y="37.7830369856935" z="2.699494370998444"/>
		<Force x="-41.34544177423257" y="7.47342244672299" z="30.88636913053749"/>
		<Force x="25.98307290500322" y="-31.21478991979773" z="27.11904752426622"/>
	</Forces>
</State>
