<?xml version="1.0" ?>
<State openmmVersion="7.3.1" time=".015" type="State" version="1">
	<PeriodicBoxVectors>
		<A x="2" y="0" z="0"/>
		<B x="0" y="2" z="0"/>
		<C x="0" y="0" z="2"/>
	</PeriodicBoxVectors>
	<Parameters/>
	<Energies KineticEnergy="8377.491967040982" PotentialEnergy="-577.9988571283005"/>
	<Positions>
		<Position x=".3385345796302495" y=".32308960614216914" z="-.25718735101329926"/>
		<Position x="-.35379197967539067" y=".5257675265500215" z="-.040870832712967556"/>
		<Position x="-.12477402849934509" y="-.21174382894276475" z="-.5815764446936644"/>
		<Position x=".6425019840922467" y="-.159985138159183" z="-.4650266397313797"/>
		<Position x="-.6132222804238376" y="-.3320864329338687" z="-1.0770497983630372"/>
		<Position x="-.44460020035632875" y="-.7930060655622007" z="-.5478845165638834"/>
		<Position x="-.9353174439646008" y="-.1361611206095184" z="-1.7658481971035496"/>
		<Position x="-.7852335963779721" y="-.8775247821303552" z="-1.7811071324581464"/>
		<Position x="-.20254232060666463" y="-.2826240148236444" z="-1.891543170440187"/>
		<Position x="-.015444230444989958" y="-.10751977188440114" z="-2.5946906221017416"/>
		<Position x=".4934648099446483" y="-.0554622164158897" z="-1.7447061774286416"/>
		<Position x=".47672967280065853" y="-.7906570696008922" z="-1.600302735396403"/>
		<Position x=".19321290627870555" y=".6035725226479874" z="-1.5486859257969592"/>
		<Position x=".9269169654291021" y=".4495087549595243" z="-1.5749189302298896"/>
		<Position x="-.38347173010666075" y=".9747607931741163" z="-1.245606639506964"/>
		<Position x="-.22109138809246406" y="1.0238757593860162" z="-1.976114765613073"/>
	</Positions>
	<Velocities>
		<Velocity x="1.032422463958993" y=".8973500109274113" z=".5942648039081178"/>
		<Velocity x="-.053816096220671295" y="-.11938408402940581" z=".13785950381461215"/>
		<Velocity x="-3.5422294527476583" y="-1.3168574455696747" z="-2.0677911694525264"/>
		<Velocity x="1.3466439578780465" y="-.15894352581346527" z=".15094119689570418"/>
		<Velocity x="2.2624965760402738" y="-.9922751243259142" z="3.843865203545871"/>
		<Velocity x="-.4460528013207732" y=".7611504315802708" z="-.9618637672810237"/>
		<Velocity x="-1.152078850787408" y=".8508102670013562" z="-1.5791398810447443"/>
		<Velocity x="-.08320133856103418" y="-.23024369189277305" z="-.07702725946345801"/>
		<Velocity x=".4568764319731078" y=".10410620703839024" z="-.18286480078080203"/>
		<Velocity x="-.1136167649104694" y=".06334489645114516" z="-.023827023856703988"/>
		<Velocity x="-.162897742344581" y="-.09114202856509851" z="-.07453510608304015"/>
		<Velocity x="-.03435568408037826" y=".014800904920342361" z="-.07640402107789157"/>
		<Velocity x=".015312787757515434" y=".022513495424347774" z=".009609145104327865"/>
		<Velocity x=".03660685910638062" y="-.02678520623216052" z=".015504678610245293"/>
		<Velocity x=".06317091558217802" y=".022774133476510805" z=".008307874482849087"/>
		<Velocity x=".1715729919627429" y="-.033621067709299624" z=".038617066589186066"/>
	</Velocities>
	<Forces>
		<Force x="-12.41617498416165" y="-23.266891261318662" z="-77.93667583028976"/>
		<Force x="-28.559440789807688" y="-19.612625945660582" z="-3.9870198840117386"/>
		<Force x="-17.536880074588662" y="5.9141696631229" z="13.834599877364802"/>
		<Force x="75.69256968460422" y="23.307107808458653" z="29.733928413432167"/>
		<Force x="-31.348579053938877" y="22.265242700270868" z="6.451181768006757"/>
		<Force x="-15.588243137826119" y="27.592033711520614" z="-5.655120692661296"/>
		<Force x="46.782936406746366" y="9.655995050842758" z="15.647007253874284"/>
		<Force x="-18.919655981509344" y="45.92050929029345" z="-30.634647783778306"/>
		<Force x="14.307789772914187" y="-1.0492262886739354" z="43.065897177362814"/>
		<Force x="-12.084824752014399" y="-25.490371614981484" z="-17.074648993567962"/>
		<Force x="-9.820824341216678" y="-19.984441834895147" z="-14.469182333242365"/>
		<Force x="60.13198804667852" y="-28.049715934624682" z="2.2141586284578985"/>
		<Force x="4.599575935374779" y="25.504709812319533" z="40.414512658736285"/>
		<Force x="-58.31802818046545" y="-6.694827011456961" z="-5.329951704861922"/>
		<Force x="24.081938480663407" y="-49.406888189519194" z="-38.78572634117606"/>
		<Force x="-21.004152991917106" y="13.395221951650505" z="42.51168397165714"/>
	</Forces>
</State>
