<?xml version="1.0" ?>
<State openmmVersion="7.3.1" time=".10500000000000002" type="State" version="1">
	<PeriodicBoxVectors>
		<A x="2" y="0" z="0"/>
		<B x="0" y="2" z="0"/>
		<C x="0" y="0" z="2"/>
	</PeriodicBoxVectors>
	<Parameters/>
	<Energies KineticEnergy="768.0220744209989" PotentialEnergy="-25.96158114872452"/>
	<Positions>
		<Position x=".005704075088678517" y=".3655387572635145" z=".06198102005106124"/>
		<Position x=".18642789050703523" y=".022959141892114295" z=".7039572366111151"/>
		<Position x="-.7180693698239417" y=".1633159327368396" z=".01659833071270841"/>
		<Position x="-.3381814074118666" y="-.47329420133845024" z="-.03944924047969309"/>
		<Position x="-.601069205423317" y=".9070618209672103" z=".16937435323071565"/>
		<Position x="-.7134686267855833" y=".8635094631123388" z="-.6004041438325564"/>
		<Position x="-.8418193596521807" y="1.0967008873581194" z=".7879291480181592"/>
		<Position x="-.20179208465042012" y=".9336106020755336" z=".8344339768657096"/>
		<Position x="-1.7668806455787418" y=".8436505588459249" z=".7449954301534822"/>
		<Position x="-1.0112971987121395" y=".4267267597601815" z=".9667812787813547"/>
		<Position x="-2.3259577663351725" y=".7763131762448557" z=".8411032388113474"/>
		<Position x="-2.7814864553229497" y="1.4120292937141028" z=".5644807247613175"/>
		<Position x="-3.1122460934315663" y=".987588563093405" z=".525116481550842"/>
		<Position x="-3.5656273586958345" y=".6730757844711489" z="1.0142275883154053"/>
		<Position x="-3.2341161933711016" y=".5687090796513694" z="-.06150322837982613"/>
		<Position x="-3.9552439222152453" y=".534120082491377" z="-.2788555779293018"/>
	</Positions>
	<Velocities>
		<Velocity x="-.01429180502713831" y="-.00535419918185065" z=".10551024880889881"/>
		<Velocity x="-.053782938374508094" y="-.032688763424004036" z=".10064980703443638"/>
		<Velocity x="-.016222424790890422" y="-.021124137254230346" z="-.017113257451659147"/>
		<Velocity x="-.09984251452543891" y="-.027662703038477954" z="-.12183604480336258"/>
		<Velocity x=".021640928623756217" y=".047134335030496466" z=".02950650319520909"/>
		<Velocity x=".16494752924343103" y="-.09750333737270633" z="-.11660983140369119"/>
		<Velocity x=".37369222871264096" y=".1324375655196608" z="-.12391543158105645"/>
		<Velocity x=".07056770593111272" y=".10218954723246743" z="-.24631990496890577"/>
		<Velocity x="-.4323989527419414" y="-.08310967099045552" z=".20195584983966341"/>
		<Velocity x=".20743964131142434" y="-.2247438602769103" z="-.05596017553741728"/>
		<Velocity x=".1229668559913577" y="-.08353602131967452" z=".2411906785832807"/>
		<Velocity x="-.07969448482425534" y=".08630657592907376" z=".18844290383062123"/>
		<Velocity x="-.16847780506639154" y=".0792688901337435" z="-.10199195764579727"/>
		<Velocity x="-.02309010868941641" y="-.023640436638738827" z="-.0771130377428264"/>
		<Velocity x="-.13360703978140265" y="-.024410895315707393" z=".04953628774917451"/>
		<Velocity x="-.132795951363196" y=".04913742606895699" z="-.017285973518388342"/>
	</Velocities>
	<Forces>
		<Force x="-6.347931175779679" y=".8398289421536536" z="-4.54612559758068"/>
		<Force x="-7.361208690557849" y="1.4837198319419602" z="-3.2737079866830454"/>
		<Force x="-.5234987143513321" y="4.191237030259835" z="5.9264982900387535"/>
		<Force x=".3268875064051464" y="4.553668444336987" z="3.1113775373757124"/>
		<Force x="1.1461134511404427" y="-2.732158919248073" z="2.273783251628622"/>
		<Force x="3.8653627540390194" y="-4.094584029001061" z="6.644935379880829"/>
		<Force x="2.595632659797943" y="-2.9308463100439504" z="-1.8554377365709775"/>
		<Force x="4.873176640167927" y="7.693300850706427" z="-1.04383890030378"/>
		<Force x="1.1329051300561472" y="-1.1773554417396292" z="-1.7731053101048002"/>
		<Force x="-2.77218979164069" y="-7.654531664673582" z="-5.407923567040748"/>
		<Force x=".7105663833803746" y="-.11534008443477381" z="-.47498742965072743"/>
		<Force x="-5.555205913878864" y="-7.870224993074368" z="-1.2938113946607426"/>
		<Force x=".3047068307485618" y="-.04176143354473942" z=".0038565239680066823"/>
		<Force x="3.240289442343326" y="3.0807931693649553" z="-4.569259430523671"/>
		<Force x="2.9127487032686252" y="4.140402020147593" z="3.327519419680161"/>
		<Force x="1.4516446805527723" y=".6338521898725191" z="2.9502267624199274"/>
	</Forces>
</State>
